streamlit_analytics_cards/__init__.py
streamlit_analytics_cards/frontend/build/asset-manifest.json
streamlit_analytics_cards/frontend/build/index.html
streamlit_analytics_cards/frontend/build/static/css/main.1c78d349.css
streamlit_analytics_cards/frontend/build/static/css/main.1c78d349.css.map
streamlit_analytics_cards/frontend/build/static/js/main.316efd9a.js
streamlit_analytics_cards/frontend/build/static/js/main.316efd9a.js.LICENSE.txt
streamlit_analytics_cards/frontend/build/static/js/main.316efd9a.js.map
streamlit_analytics_cards-0.1.6.dist-info/METADATA
streamlit_analytics_cards-0.1.6.dist-info/WHEEL
streamlit_analytics_cards-0.1.6.dist-info/top_level.txt
streamlit_analytics_cards-0.1.6.dist-info/RECORD
