Metadata-Version: 2.2
Name: streamlit-analytics-cards
Version: 0.1.6
Summary: A custom Streamlit component for analytics cards
Home-page: https://github.com/natxc/streamlit-analytics-cards
Author: Natalie C
Classifier: Programming Language :: Python :: 3
Classifier: License :: OSI Approved :: MIT License
Classifier: Operating System :: OS Independent
Requires-Python: >=3.7
Requires-Dist: streamlit
Requires-Dist: cachetools
Dynamic: author
Dynamic: classifier
Dynamic: description
Dynamic: description-content-type
Dynamic: home-page
Dynamic: requires-dist
Dynamic: requires-python
Dynamic: summary
